[{"sampleID":"TCGA-BC-A10Q","PC1":-6.5949,"PC2":0.2637,"PC3":-1.7823,"group":"LIHC","gender":"FEMALE","stage":"[NA]","vital":"Dead","neg3":"[NA]","url":"./data/TCGA/LIHC/TCGA-BC-A10Q.json"},{"sampleID":"TCGA-BC-A10R","PC1":0.3286,"PC2":-2.3859,"PC3":1.2665,"group":"LIHC","gender":"FEMALE","stage":"[NA]","vital":"Dead","neg3":"[NA]","url":"./data/TCGA/LIHC/TCGA-BC-A10R.json"},{"sampleID":"TCGA-BC-A10T","PC1":4.9995,"PC2":-0.5051,"PC3":-2.6813,"group":"LIHC","gender":"MALE","stage":"[NA]","vital":"Dead","neg3":"[NA]","url":"./data/TCGA/LIHC/TCGA-BC-A10T.json"},{"sampleID":"TCGA-BC-A10U","PC1":0.2219,"PC2":-0.373,"PC3":3.5625,"group":"LIHC","gender":"MALE","stage":"[NA]","vital":"Dead","neg3":"[NA]","url":"./data/TCGA/LIHC/TCGA-BC-A10U.json"},{"sampleID":"TCGA-BC-A10W","PC1":1.0534,"PC2":4.8557,"PC3":0.4155,"group":"LIHC","gender":"MALE","stage":"[NA]","vital":"Dead","neg3":"[NA]","url":"./data/TCGA/LIHC/TCGA-BC-A10W.json"},{"sampleID":"TCGA-BC-A10X","PC1":-0.0085,"PC2":-1.8554,"PC3":-0.7808,"group":"LIHC","gender":"FEMALE","stage":"Stage III","vital":"Dead","neg3":"[NA]","url":"./data/TCGA/LIHC/TCGA-BC-A10X.json"}]
